{
    "data": [
                {
                "asset_id": "5bda985605744f160b52411a",
                "asset_type": "Identity Card",
                "parrent_asset_type": "Identity",
                "properties": {
                        "address": "S/O: Prem Chand Jayaswal, 566, 566, Mally Banetha, Tonk, Rajasthan 304024",
                        "birth_date": "1992-07-19",
                        "distance_from_geo_location": "9229596.331344698",
                        "files": ["http://192.168.10.32:8000/get-image/?file=5bda985405744f160b524110",
                                    "http://192.168.10.32:8000/get-image/?file=5bda985505744f160b524115"
                                ],
                        "first_name": "Ankit",
                        "gender": "Male",
                        "geo_address": "Jaipur, Jaipur - 302001, Rajasthan, India",
                        "geo_latitude": "26.778666455214523",
                        "geo_longitude": "75.84149069364277",
                        "identity_number": "3553 7502 9367",
                        "last_name": "Jayaswal",
                        "latitude": "75.58333",
                        "longitude": "26.16667",
                        "middle_name": "Kumar",
                        "nationality": "India"
                },
                "verification_status": "REJECTED"
            }
    ]
}
